mtoolnote/__init__.py
mtoolnote/classes.py
mtoolnote/cli.py
mtoolnote/constants.py
mtoolnote/human.py
mtoolnote/models.py
mtoolnote/mtoolnote.py
mtoolnote/nonhuman.py
mtoolnote/update_frequency.py
mtoolnote/data/mtoolnote.db
mtoolnote-0.2.0.dist-info/AUTHORS.rst
mtoolnote-0.2.0.dist-info/LICENSE
mtoolnote-0.2.0.dist-info/METADATA
mtoolnote-0.2.0.dist-info/WHEEL
mtoolnote-0.2.0.dist-info/entry_points.txt
mtoolnote-0.2.0.dist-info/top_level.txt
mtoolnote-0.2.0.dist-info/RECORD
