Metadata-Version: 2.1
Name: mtoolnote
Version: 0.2.0
Summary: Variant annotator for MToolBox.
Home-page: https://github.com/mitoNGS/mtoolnote
Author: Roberto Preste
Author-email: robertopreste@gmail.com
License: MIT license
Keywords: mtoolnote
Platform: UNKNOWN
Classifier: Development Status :: 2 - Pre-Alpha
Classifier: Intended Audience :: Developers
Classifier: License :: OSI Approved :: MIT License
Classifier: Natural Language :: English
Classifier: Programming Language :: Python :: 3
Classifier: Programming Language :: Python :: 3.6
Classifier: Programming Language :: Python :: 3.7
Requires-Dist: Click
Requires-Dist: pandas
Requires-Dist: requests
Requires-Dist: aiohttp
Requires-Dist: pysam
Requires-Dist: vcfpy
Requires-Dist: sqlalchemy
Requires-Dist: apybiomart
Requires-Dist: scikit-allel
